testcase_uploader/__init__.py
testcase_uploader/urls.py
testcase_uploader/views.py
testcase_uploader/templates/upload.html
testcase_uploader/xlsx_parser_lib/__init__.py
testcase_uploader/xlsx_parser_lib/exceptions.py
testcase_uploader/xlsx_parser_lib/xlsx_parser.py
testcase_uploader-0.1.0.dist-info/METADATA
testcase_uploader-0.1.0.dist-info/WHEEL
testcase_uploader-0.1.0.dist-info/entry_points.txt
testcase_uploader-0.1.0.dist-info/top_level.txt
testcase_uploader-0.1.0.dist-info/RECORD
