Metadata-Version: 2.4
Name: testcase-uploader
Version: 0.1.0
Summary: Testcase uploader plugin for TestY
Requires-Dist: openpyxl==3.1.1
Dynamic: requires-dist
Dynamic: summary
